secrets_storage/__init__.py
secrets_storage/storages.py
secrets_storage/version.py
tests/__init__.py
tests/test_env_storage.py
tests/test_sercrets.py
tests/test_vault_storage.py
secrets_storage-0.11.0.dist-info/LICENSE
secrets_storage-0.11.0.dist-info/METADATA
secrets_storage-0.11.0.dist-info/WHEEL
secrets_storage-0.11.0.dist-info/top_level.txt
secrets_storage-0.11.0.dist-info/RECORD
